pybuzzers/BuzzerSet.py
pybuzzers/__init__.py
pybuzzers/pybuzzers.py
pybuzzers-1.0.6.dist-info/LICENSE
pybuzzers-1.0.6.dist-info/METADATA
pybuzzers-1.0.6.dist-info/WHEEL
pybuzzers-1.0.6.dist-info/top_level.txt
pybuzzers-1.0.6.dist-info/RECORD
