Metadata-Version: 2.1
Name: pybuzzers
Version: 1.0.6
Summary: Event-driven Python package for interfacing with Sony Buzz! buzzer sets.
Author-email: Cailean Wilkinson <cjw27@st-andrews.ac.uk>
Project-URL: Homepage, https://github.com/CaileanWilkinson/pybuzzers
Project-URL: Bug Tracker, https://github.com/CaileanWilkinson/pybuzzers/issues
Classifier: Programming Language :: Python :: 3
Classifier: License :: OSI Approved :: MIT License
Classifier: Operating System :: OS Independent
Requires-Python: >=3.7
License-File: LICENSE
Requires-Dist: hidapi
